{"id":"A2T1","dependencies":[{"name":"/Users/stephengheysens/Documents/Projects/dcEats/package.json","includedInParent":true,"mtime":1534348395531},{"name":"./master.scss","loc":{"line":1,"column":7},"parent":"/Users/stephengheysens/Documents/Projects/dcEats/app.js","resolved":"/Users/stephengheysens/Documents/Projects/dcEats/master.scss"}],"generated":{"js":"\"use strict\";require(\"./master.scss\");var e=document.getElementById(\"pizza\");e.addEventListener(\"click\",function(e){return alert(\"Mmm... pizzaaa.\")}),mapboxgl.accessToken=\"pk.eyJ1Ijoic2VnaGV5c2VucyIsImEiOiJjamtkaTM1c3UwMWd6M3JudnNic2xlNzNyIn0.ev497aFfqUil1_90BzrJQQ\";var a=new mapboxgl.Map({container:\"map\",style:\"mapbox://styles/segheysens/cjkujjvr30rjl2sldh342cb1i\",center:[-77.035,38.891],zoom:11});console.log(\"mama, we made it\");","map":{"mappings":[{"source":"app.js","original":{"line":14,"column":0},"generated":{"line":1,"column":0}},{"source":"app.js","original":{"line":1,"column":0},"generated":{"line":1,"column":13}},{"source":"app.js","original":{"line":1,"column":0},"generated":{"line":1,"column":21}},{"source":"app.js","original":{"line":3,"column":0},"generated":{"line":1,"column":38}},{"source":"app.js","name":"pizza","original":{"line":3,"column":6},"generated":{"line":1,"column":42}},{"source":"app.js","name":"document","original":{"line":3,"column":14},"generated":{"line":1,"column":44}},{"source":"app.js","name":"getElementById","original":{"line":3,"column":23},"generated":{"line":1,"column":53}},{"source":"app.js","original":{"line":3,"column":38},"generated":{"line":1,"column":68}},{"source":"app.js","name":"pizza","original":{"line":4,"column":0},"generated":{"line":1,"column":77}},{"source":"app.js","name":"addEventListener","original":{"line":4,"column":6},"generated":{"line":1,"column":79}},{"source":"app.js","original":{"line":4,"column":23},"generated":{"line":1,"column":96}},{"source":"app.js","original":{"line":4,"column":32},"generated":{"line":1,"column":104}},{"source":"app.js","name":"e","original":{"line":4,"column":33},"generated":{"line":1,"column":113}},{"source":"app.js","name":"alert","original":{"line":4,"column":39},"generated":{"line":1,"column":116}},{"source":"app.js","name":"alert","original":{"line":4,"column":39},"generated":{"line":1,"column":123}},{"source":"app.js","original":{"line":4,"column":45},"generated":{"line":1,"column":129}},{"source":"app.js","name":"mapboxgl","original":{"line":6,"column":0},"generated":{"line":1,"column":150}},{"source":"app.js","name":"accessToken","original":{"line":6,"column":9},"generated":{"line":1,"column":159}},{"source":"app.js","original":{"line":6,"column":23},"generated":{"line":1,"column":171}},{"source":"app.js","original":{"line":7,"column":0},"generated":{"line":1,"column":267}},{"source":"app.js","name":"map","original":{"line":7,"column":6},"generated":{"line":1,"column":271}},{"source":"app.js","original":{"line":7,"column":12},"generated":{"line":1,"column":273}},{"source":"app.js","name":"mapboxgl","original":{"line":7,"column":16},"generated":{"line":1,"column":277}},{"source":"app.js","name":"Map","original":{"line":7,"column":25},"generated":{"line":1,"column":286}},{"source":"app.js","original":{"line":7,"column":29},"generated":{"line":1,"column":290}},{"source":"app.js","original":{"line":8,"column":13},"generated":{"line":1,"column":291}},{"source":"app.js","original":{"line":8,"column":13},"generated":{"line":1,"column":301}},{"source":"app.js","original":{"line":9,"column":9},"generated":{"line":1,"column":307}},{"source":"app.js","original":{"line":9,"column":9},"generated":{"line":1,"column":313}},{"source":"app.js","original":{"line":10,"column":10},"generated":{"line":1,"column":368}},{"source":"app.js","original":{"line":10,"column":10},"generated":{"line":1,"column":375}},{"source":"app.js","original":{"line":10,"column":12},"generated":{"line":1,"column":377}},{"source":"app.js","original":{"line":10,"column":20},"generated":{"line":1,"column":384}},{"source":"app.js","original":{"line":11,"column":8},"generated":{"line":1,"column":392}},{"source":"app.js","original":{"line":11,"column":8},"generated":{"line":1,"column":397}},{"source":"app.js","name":"console","original":{"line":14,"column":0},"generated":{"line":1,"column":402}},{"source":"app.js","name":"log","original":{"line":14,"column":8},"generated":{"line":1,"column":410}},{"source":"app.js","original":{"line":14,"column":12},"generated":{"line":1,"column":414}}],"sources":{"app.js":"import './master.scss';\n\nconst pizza = document.getElementById(\"pizza\");\npizza.addEventListener(\"click\", (e) => alert(\"Mmm... pizzaaa.\") );\n\nmapboxgl.accessToken = 'pk.eyJ1Ijoic2VnaGV5c2VucyIsImEiOiJjamtkaTM1c3UwMWd6M3JudnNic2xlNzNyIn0.ev497aFfqUil1_90BzrJQQ';\nconst map = new mapboxgl.Map({\n  container: 'map',\n  style: 'mapbox://styles/segheysens/cjkujjvr30rjl2sldh342cb1i',\n  center: [-77.035, 38.891],\n  zoom: 11\n});\n\nconsole.log(\"mama, we made it\");\n"},"lineCount":null}},"hash":"5da9c63e17376b668dbf083a765d8f47","cacheData":{"env":{}}}